mir/__init__.py
mir/_impl.py
mir/bootstrap.min.css
mir/bootstrap.min.js
mir/custom.css
mir/custom.js
mir/jquery.min.js
mir/markdown-it.min.js
mir/report_html.tpl
mir/script.py
markdown_it_reporter-0.0.2.dist-info/METADATA
markdown_it_reporter-0.0.2.dist-info/WHEEL
markdown_it_reporter-0.0.2.dist-info/entry_points.txt
markdown_it_reporter-0.0.2.dist-info/top_level.txt
markdown_it_reporter-0.0.2.dist-info/RECORD
