Metadata-Version: 2.1
Name: markdown-it-reporter
Version: 0.0.2
Summary: Galaxy Workflow Format 2 Descriptions
Home-page: https://github.com/galaxyproject/markdown-it-reporter
Author: Galaxy Project and Community
Author-email: jmchilton@gmail.com
License: AFL
Keywords: galaxy
Platform: UNKNOWN
Classifier: Development Status :: 5 - Production/Stable
Classifier: Intended Audience :: Developers
Classifier: Environment :: Console
Classifier: License :: OSI Approved :: Academic Free License (AFL)
Classifier: Operating System :: POSIX
Classifier: Topic :: Software Development
Classifier: Topic :: Software Development :: Code Generators
Classifier: Topic :: Software Development :: Testing
Classifier: Natural Language :: English
Classifier: Programming Language :: Python :: 3
Classifier: Programming Language :: Python :: 3.5
Classifier: Programming Language :: Python :: 3.6
Classifier: Programming Language :: Python :: 3.7
Classifier: Programming Language :: Python :: 3.8
Requires-Dist: jinja2
